Metadata-Version: 2.1
Name: DouBaoChat
Version: 1.0.2
Summary: DouBaoChat is a simple encapsulation for the official DouBao API
Home-page: https://github.com/umbrella-leaf/DouBaoChat
Author: Zhongnuo Liu
Author-email: 2313678365@qq.com
License: Apache-2.0 license
Keywords: API,DouBao
Classifier: Development Status :: 3 - Alpha
Classifier: License :: OSI Approved :: Apache Software License
Classifier: Intended Audience :: Developers
Classifier: Intended Audience :: End Users/Desktop
Classifier: Natural Language :: English
Classifier: Topic :: Software Development :: Libraries :: Python Modules
Classifier: Programming Language :: Python :: 3 :: Only
Classifier: Programming Language :: Python :: 3.6
Classifier: Programming Language :: Python :: 3.7
Classifier: Programming Language :: Python :: 3.8
Classifier: Programming Language :: Python :: 3.9
Classifier: Programming Language :: Python :: 3.10
Classifier: Programming Language :: Python :: 3.11
License-File: LICENSE
Requires-Dist: volcengine-python-sdk[ark]==1.0.93
Requires-Dist: httpx==0.27.0
Requires-Dist: pydantic==1.9.0
